org_todo_send/__init__.py
org_todo_send/main.py
org_todo_send/parse.py
org_todo_send-0.1.2.dist-info/METADATA
org_todo_send-0.1.2.dist-info/WHEEL
org_todo_send-0.1.2.dist-info/entry_points.txt
org_todo_send-0.1.2.dist-info/RECORD
