Metadata-Version: 2.1
Name: org-todo-send
Version: 0.1.2
Summary: A CLI tool which sends TODOs from an Org file to people they have been assigned to via the Signal REST API
Author: Ammar Nanjiani
Author-email: ammar.nanjiani@gmail.com
Requires-Python: >=3.11,<4.0
Classifier: Programming Language :: Python :: 3
Classifier: Programming Language :: Python :: 3.11
Classifier: Programming Language :: Python :: 3.12
Requires-Dist: orgparse (>=0.4.20231004,<0.5.0)
Requires-Dist: pandas (>=2.2.1,<3.0.0)
Requires-Dist: pypandoc-binary (>=1.13,<2.0)
Requires-Dist: pysignalclirestapi (>=0.3.23,<0.4.0)
Requires-Dist: requests (>=2.31.0,<3.0.0)
Requires-Dist: typer[all] (>=0.12.3,<0.13.0)
